openbudget/__init__.py
openbudget/__main__.py
openbudget/cli.py
OpenBudget-0.0.2.dist-info/AUTHORS.rst
OpenBudget-0.0.2.dist-info/LICENSE
OpenBudget-0.0.2.dist-info/METADATA
OpenBudget-0.0.2.dist-info/NOTICE.py
OpenBudget-0.0.2.dist-info/WHEEL
OpenBudget-0.0.2.dist-info/entry_points.txt
OpenBudget-0.0.2.dist-info/top_level.txt
OpenBudget-0.0.2.dist-info/RECORD
