Metadata-Version: 2.1
Name: OpenBudget
Version: 0.0.2
Summary: Simple budget management planner
Home-page: https://gitlab.yapbreak.fr/olivaa/openbudget
Author: Adrien Oliva
Author-email: olivaa@yapbreak.fr
License: GNU/GPL v3
Keywords: openbudget
Platform: UNKNOWN
Classifier: Development Status :: 1 - Planning
Classifier: Environment :: Console
Classifier: License :: OSI Approved :: GNU General Public License v3 (GPLv3)
Classifier: Programming Language :: Python
Classifier: Programming Language :: Python :: 3
Classifier: Programming Language :: Python :: 3.4
Classifier: Programming Language :: Python :: 3.5
Classifier: Programming Language :: Python :: 3.6
Classifier: Programming Language :: Python :: 3.7
Requires-Python: >=3.4
Requires-Dist: Click
